[
  {
    "changeuuid": "abbb72a9-a4e3-4c37-be29-73128b23d844",
    "stationuuid": "ffc3b335-f821-4ef1-b694-49aec6143d0b",
    "serveruuid": "761bd33c-3a09-466f-80e5-18984c59eaf2",
    "name": "Abdulbasit Abdulsamad",
    "url": "https://radio.mp3islam.com/listen/abdulbasit/radio.mp3",
    "url_resolved": "https://radio.mp3islam.com/listen/abdulbasit/radio.mp3",
    "homepage": "https://mp3islam.com/",
    "favicon": "null",
    "tags": "",
    "country": "Mongolia",
    "countrycode": "MN",
    "iso_3166_2": "",
    "state": "",
    "language": "arabic",
    "languagecodes": "ar",
    "votes": 19,
    "lastchangetime": "2025-06-13 06:39:16",
    "lastchangetime_iso8601": "2025-06-13T06:39:16Z",
    "codec": "MP3",
    "bitrate": 192,
    "hls": 0,
    "lastcheckok": 1,
    "lastchecktime": "2025-06-25 08:03:22",
    "lastchecktime_iso8601": "2025-06-25T08:03:22Z",
    "lastcheckoktime": "2025-06-25 08:03:22",
    "lastcheckoktime_iso8601": "2025-06-25T08:03:22Z",
    "lastlocalchecktime": "2025-06-25 08:03:22",
    "lastlocalchecktime_iso8601": "2025-06-25T08:03:22Z",
    "clicktimestamp": "2025-06-22 11:35:49",
    "clicktimestamp_iso8601": "2025-06-22T11:35:49Z",
    "clickcount": 7,
    "clicktrend": 0,
    "ssl_error": 0,
    "geo_lat": null,
    "geo_long": null,
    "geo_distance": null,
    "has_extended_info": false
  },
  {
    "changeuuid": "c6cef632-cca2-49e3-845f-5cc713aae75c",
    "stationuuid": "d4f76b86-f6ce-4103-b1ab-0f78d300245b",
    "serveruuid": "ed6bc1de-f910-4155-a127-c55a5ccd5116",
    "name": "Best FM",
    "url": "http://103.48.116.109:9000/;",
    "url_resolved": "http://103.48.116.109:9000/;",
    "homepage": "http://www.bestfm.mn/",
    "favicon": "https://cdn.onlineradiobox.com/img/l/3/72103.v4.png",
    "tags": "music",
    "country": "Mongolia",
    "countrycode": "MN",
    "iso_3166_2": "",
    "state": "",
    "language": "",
    "languagecodes": "",
    "votes": 53,
    "lastchangetime": "2025-06-12 17:54:18",
    "lastchangetime_iso8601": "2025-06-12T17:54:18Z",
    "codec": "MP3",
    "bitrate": 128,
    "hls": 0,
    "lastcheckok": 1,
    "lastchecktime": "2025-06-25 04:55:53",
    "lastchecktime_iso8601": "2025-06-25T04:55:53Z",
    "lastcheckoktime": "2025-06-25 04:55:53",
    "lastcheckoktime_iso8601": "2025-06-25T04:55:53Z",
    "lastlocalchecktime": "2025-06-25 04:55:53",
    "lastlocalchecktime_iso8601": "2025-06-25T04:55:53Z",
    "clicktimestamp": "2025-06-24 09:31:46",
    "clicktimestamp_iso8601": "2025-06-24T09:31:46Z",
    "clickcount": 26,
    "clicktrend": -4,
    "ssl_error": 0,
    "geo_lat": null,
    "geo_long": null,
    "geo_distance": null,
    "has_extended_info": false
  },
  {
    "changeuuid": "e4ba6fcb-9447-4a8d-b792-3ea8972b1778",
    "stationuuid": "b1aae7b8-8916-4016-b57a-c2bb08704510",
    "serveruuid": "a528f2fb-f70c-41ea-aa53-62883c413046",
    "name": "Family Radio FM",
    "url": "https://c2.radioboss.fm/stream/394",
    "url_resolved": "https://c2.radioboss.fm/stream/394",
    "homepage": "https://www.facebook.com/gerbulradio/",
    "favicon": "https://www.facebook.com/favicon.ico",
    "tags": "talk",
    "country": "Mongolia",
    "countrycode": "MN",
    "iso_3166_2": "",
    "state": "",
    "language": "monoglian",
    "languagecodes": "",
    "votes": 423,
    "lastchangetime": "2025-06-12 17:54:17",
    "lastchangetime_iso8601": "2025-06-12T17:54:17Z",
    "codec": "MP3",
    "bitrate": 128,
    "hls": 0,
    "lastcheckok": 1,
    "lastchecktime": "2025-06-25 07:49:29",
    "lastchecktime_iso8601": "2025-06-25T07:49:29Z",
    "lastcheckoktime": "2025-06-25 07:49:29",
    "lastcheckoktime_iso8601": "2025-06-25T07:49:29Z",
    "lastlocalchecktime": "2025-06-25 07:49:29",
    "lastlocalchecktime_iso8601": "2025-06-25T07:49:29Z",
    "clicktimestamp": "2025-06-24 05:00:37",
    "clicktimestamp_iso8601": "2025-06-24T05:00:37Z",
    "clickcount": 23,
    "clicktrend": -1,
    "ssl_error": 0,
    "geo_lat": null,
    "geo_long": null,
    "geo_distance": null,
    "has_extended_info": false
  },
  {
    "changeuuid": "5eda6e9b-282b-4757-9167-598e22c81e54",
    "stationuuid": "fa31e2f5-8092-11e9-aa30-52543be04c81",
    "serveruuid": "d5eff2bb-0cbb-45b9-8de6-3b214ad91002",
    "name": "MGL Radio",
    "url": "http://stream17.shoutcastsolutions.com:8096/",
    "url_resolved": "http://stream17.shoutcastsolutions.com:8096/",
    "homepage": "http://mglradio.com/",
    "favicon": "",
    "tags": "",
    "country": "Mongolia",
    "countrycode": "MN",
    "iso_3166_2": "",
    "state": "Ulaanbaatar",
    "language": "mongolian",
    "languagecodes": "mn",
    "votes": 1277,
    "lastchangetime": "2025-06-13 06:05:02",
    "lastchangetime_iso8601": "2025-06-13T06:05:02Z",
    "codec": "MP3",
    "bitrate": 128,
    "hls": 0,
    "lastcheckok": 1,
    "lastchecktime": "2025-06-25 00:13:39",
    "lastchecktime_iso8601": "2025-06-25T00:13:39Z",
    "lastcheckoktime": "2025-06-25 00:13:39",
    "lastcheckoktime_iso8601": "2025-06-25T00:13:39Z",
    "lastlocalchecktime": "2025-06-25 00:13:39",
    "lastlocalchecktime_iso8601": "2025-06-25T00:13:39Z",
    "clicktimestamp": "2025-06-25 08:42:01",
    "clicktimestamp_iso8601": "2025-06-25T08:42:01Z",
    "clickcount": 38,
    "clicktrend": -1,
    "ssl_error": 0,
    "geo_lat": null,
    "geo_long": null,
    "geo_distance": null,
    "has_extended_info": false
  },
  {
    "changeuuid": "7cd072f6-6f2e-4616-98a2-305eabbf7b60",
    "stationuuid": "e7223f6a-0ee8-4c3f-9a10-977fae786d79",
    "serveruuid": "7049f4d5-2527-4659-a092-85d3878d2269",
    "name": "Mongolian Music Radio",
    "url": "http://65.108.143.81:7700/1",
    "url_resolved": "http://65.108.143.81:7700/1",
    "homepage": "https://www.radiosons.com/",
    "favicon": "https://static2.mytuner.mobi/media/tvos_radios/hgBdpd39Rk.png",
    "tags": "electro,pop,rock,top 40",
    "country": "Mongolia",
    "countrycode": "MN",
    "iso_3166_2": "",
    "state": "Web",
    "language": "mongolian",
    "languagecodes": "mn",
    "votes": 40,
    "lastchangetime": "2025-06-12 19:53:55",
    "lastchangetime_iso8601": "2025-06-12T19:53:55Z",
    "codec": "MP3",
    "bitrate": 128,
    "hls": 0,
    "lastcheckok": 1,
    "lastchecktime": "2025-06-25 07:44:41",
    "lastchecktime_iso8601": "2025-06-25T07:44:41Z",
    "lastcheckoktime": "2025-06-25 07:44:41",
    "lastcheckoktime_iso8601": "2025-06-25T07:44:41Z",
    "lastlocalchecktime": "2025-06-24 21:46:47",
    "lastlocalchecktime_iso8601": "2025-06-24T21:46:47Z",
    "clicktimestamp": "2025-06-25 08:40:59",
    "clicktimestamp_iso8601": "2025-06-25T08:40:59Z",
    "clickcount": 53,
    "clicktrend": -3,
    "ssl_error": 0,
    "geo_lat": null,
    "geo_long": null,
    "geo_distance": null,
    "has_extended_info": false
  },
  {
    "changeuuid": "1911b337-4577-4b88-b326-29ee3f09303b",
    "stationuuid": "78ea6284-d457-439a-b133-f35a444d895b",
    "serveruuid": "a528f2fb-f70c-41ea-aa53-62883c413046",
    "name": "Гэр бүлийн радио 104.5",
    "url": "https://c2.radioboss.fm/stream/394",
    "url_resolved": "https://c2.radioboss.fm/stream/394",
    "homepage": "https://1045.mn/",
    "favicon": "https://encrypted-tbn0.gstatic.com/images?q=tbn:ANd9GcRJc5-ql9EF8iTlZNwePtu7WkuZHhgyiCSp6A&s",
    "tags": "christian,community,culture",
    "country": "Mongolia",
    "countrycode": "MN",
    "iso_3166_2": "",
    "state": "",
    "language": "mongolian",
    "languagecodes": "mn",
    "votes": 28,
    "lastchangetime": "2025-06-12 22:41:17",
    "lastchangetime_iso8601": "2025-06-12T22:41:17Z",
    "codec": "MP3",
    "bitrate": 128,
    "hls": 0,
    "lastcheckok": 1,
    "lastchecktime": "2025-06-25 00:26:53",
    "lastchecktime_iso8601": "2025-06-25T00:26:53Z",
    "lastcheckoktime": "2025-06-25 00:26:53",
    "lastcheckoktime_iso8601": "2025-06-25T00:26:53Z",
    "lastlocalchecktime": "2025-06-25 00:26:53",
    "lastlocalchecktime_iso8601": "2025-06-25T00:26:53Z",
    "clicktimestamp": "2025-06-24 09:32:56",
    "clicktimestamp_iso8601": "2025-06-24T09:32:56Z",
    "clickcount": 17,
    "clicktrend": -1,
    "ssl_error": 0,
    "geo_lat": null,
    "geo_long": null,
    "geo_distance": null,
    "has_extended_info": false
  },
  {
    "changeuuid": "90109fe3-18b4-4d25-a149-095db9e7d97e",
    "stationuuid": "83cd32c9-2461-468f-afe8-4be8e5a4ee23",
    "serveruuid": "3a1eaf44-6d04-4c4a-812c-bf623f3aa5e7",
    "name": "内蒙古草原之声 Inner Mongolia Voice of Grassland",
    "url": "https://lhttp-hw.qtfm.cn/live/20973/64k.mp3",
    "url_resolved": "https://lhttp-hw.qtfm.cn/live/20973/64k.mp3",
    "homepage": "https://www.nmtv.cn/",
    "favicon": "https://pic.qtfm.cn/2015/0324/20150324134256614.jpg",
    "tags": "culture",
    "country": "Mongolia",
    "countrycode": "MN",
    "iso_3166_2": "",
    "state": "",
    "language": "mongolian",
    "languagecodes": "mn",
    "votes": 15,
    "lastchangetime": "2025-06-13 01:37:06",
    "lastchangetime_iso8601": "2025-06-13T01:37:06Z",
    "codec": "MP3",
    "bitrate": 0,
    "hls": 0,
    "lastcheckok": 1,
    "lastchecktime": "2025-06-25 07:06:05",
    "lastchecktime_iso8601": "2025-06-25T07:06:05Z",
    "lastcheckoktime": "2025-06-25 07:06:05",
    "lastcheckoktime_iso8601": "2025-06-25T07:06:05Z",
    "lastlocalchecktime": "2025-06-25 06:19:01",
    "lastlocalchecktime_iso8601": "2025-06-25T06:19:01Z",
    "clicktimestamp": "2025-06-25 08:41:05",
    "clicktimestamp_iso8601": "2025-06-25T08:41:05Z",
    "clickcount": 41,
    "clicktrend": 2,
    "ssl_error": 0,
    "geo_lat": null,
    "geo_long": null,
    "geo_distance": null,
    "has_extended_info": false
  }
]